vlora/__init__.py
vlora/models/__init__.py
vlora/models/common.py
vlora/models/transformer.py
vlora/models/vit.py
vlora/utils/__init__.py
vlora/utils/vlorafy.py
vlora-0.1.2.dist-info/METADATA
vlora-0.1.2.dist-info/WHEEL
vlora-0.1.2.dist-info/RECORD
