Metadata-Version: 2.1
Name: vlora
Version: 0.1.2
Summary: 
Author: neverusethisname
Author-email: 13056660723@163.com
Requires-Python: >=3.10,<4.0
Classifier: Programming Language :: Python :: 3
Classifier: Programming Language :: Python :: 3.10
Classifier: Programming Language :: Python :: 3.11
Classifier: Programming Language :: Python :: 3.12
Requires-Dist: timm (>=0.9.16,<0.10.0)
